[{"lat": "-2856.716", "project": "GINA2019_1", "t_mission": 182, "altim_ping_depth": 100, "sim_pitch": 0, "dive_number": 47, "gc_roll_errors": 0, "d_abort": 1050, "platform_id": "SG573", "wp_lat": "0", "d_tgt": 500, "gpsTime": "010170000000", "start_time": 1554151296, "c_roll_dive": 1987, "c_vbd": 2812, "gc_pitch_errors": 0, "t_dive": 167, "glider": 573, "t_abort": 197, "gc_vbd_errors": 0, "sm_cc": 542, "gc_vbd_retries": 0, "start_time_human": "01-04-2019 20:41:36", "c_roll_climb": 1987, "max_buoy": 150, "gc_roll_retries": 0, "c_pitch": 2490, "gc_pitch_retries": 0, "instruments": "magnetometer wlbb2fl aa4831 sbe41 qsp2150 ", "lon": "3212.875", "file_name": "sg573_30_data.json", "mission_number": 30}]