[{"max_buoy": 150, "wp_lat": "0", "start_time": 1554348372, "gc_pitch_retries": 0, "gc_roll_retries": 0, "start_time_human": "04-04-2019 03:26:12", "lat": "-2902.579", "sim_pitch": 0, "project": "GINA2019_1", "gpsTime": "010170000000", "dive_number": 88, "t_dive": 333, "d_abort": 1050, "gc_pitch_errors": 0, "gc_vbd_retries": 0, "c_roll_climb": 1987, "lon": "3210.627", "t_abort": 358, "gc_roll_errors": 0, "mission_number": 30, "d_tgt": 1000, "t_mission": 343, "sm_cc": 542, "platform_id": "SG573", "file_name": "sg573_30_data.json", "altim_ping_depth": 50, "glider": 573, "c_pitch": 2490, "c_vbd": 2812, "c_roll_dive": 1987, "instruments": "magnetometer wlbb2fl aa4831 sbe41 ", "gc_vbd_errors": 0}]