[{"sim_pitch": 0, "lat": "-3027.107", "start_time": 1554155767, "instruments": "sbe41 aa4330 wlbb2fl qsp2150 ", "max_buoy": 95, "platform_id": "SG574", "mission_number": 3, "glider": 574, "gc_pitch_errors": 0, "gc_vbd_errors": 0, "gc_roll_errors": 0, "d_abort": 1020, "gc_pitch_retries": 0, "t_abort": 197, "start_time_human": "01-04-2019 21:56:07", "gc_vbd_retries": 0, "sm_cc": 515, "file_name": "sg574_3_data.json", "lon": "3103.402", "c_roll_climb": 1800, "gpsTime": "010170000000", "c_vbd": 2701, "gc_roll_retries": 0, "t_mission": 182, "altim_ping_depth": 50, "d_tgt": 500, "c_roll_dive": 1812, "t_dive": 167, "project": "GINA2019_1", "c_pitch": 2759, "dive_number": 226, "wp_lat": "0"}]