[{"c_pitch": 2490, "d_tgt": 30, "c_roll_dive": 1987, "start_time": 1551772103, "sm_cc": 532, "c_roll_climb": 1987, "gc_pitch_errors": 0, "platform_id": "SG573", "wp_lat": "0", "glider": 573, "altim_ping_depth": 10, "instruments": "magnetometer wlbb2fl aa4831 sbe41 qsp2150 ", "gc_roll_retries": 0, "gpsTime": "010170000000", "gc_roll_errors": 0, "mission_number": 26, "d_abort": 100, "project": "GINA2019_seatrials", "max_buoy": 200, "gc_vbd_retries": 0, "sim_pitch": -20, "dive_number": 7, "lon": "1825.630", "start_time_human": "05-03-2019 07:48:23", "file_name": "sg573_26_data.json", "gc_pitch_retries": 0, "c_vbd": 2812, "lat": "-3354.152", "t_mission": 25, "t_abort": 40, "t_dive": 10, "gc_vbd_errors": 0}]