[{"project": "GINA2018", "lon": "3117.832", "t_abort": 268, "c_pitch": 2490, "c_roll_dive": 2130, "start_time": 1537901703, "gc_pitch_retries": 0, "c_vbd": 2812, "max_buoy": 150, "gpsTime": "010170000000", "t_dive": 234, "d_tgt": 500, "t_mission": 249, "glider": 573, "lat": "-2954.667", "mission_number": 22, "c_roll_climb": 1910, "gc_roll_retries": 0, "gc_vbd_retries": 0, "file_name": "sg573_22_data.json", "gc_roll_errors": 0, "dive_number": 157, "wp_lat": "-2953.98", "altim_ping_depth": 100, "d_abort": 1050, "sm_cc": 290, "start_time_human": "25-09-2018 18:55:03", "platform_id": "SG573", "sim_pitch": 0, "instruments": "magnetometer wlbb2fl aa4831 sbe41 qsp2150 ", "gc_vbd_errors": 0, "gc_pitch_errors": 0, "wp_lon": "3117.47"}]