[{"wp_lat": "0", "start_time_human": "19-04-2019 02:44:10", "c_vbd": 2701, "glider": 574, "project": "GINA2019_1", "file_name": "sg574_3_data.json", "platform_id": "SG574", "t_dive": 333, "c_roll_dive": 1812, "sim_pitch": 0, "dive_number": 434, "gc_roll_errors": 0, "gc_vbd_errors": 0, "altim_ping_depth": 50, "gc_roll_retries": 0, "gc_vbd_retries": 0, "gpsTime": "010170000000", "max_buoy": 200, "d_tgt": 1000, "gc_pitch_retries": 0, "mission_number": 3, "c_pitch": 2759, "c_roll_climb": 1800, "start_time": 1555641850, "t_abort": 358, "lon": "2523.566", "d_abort": 1020, "sm_cc": 515, "instruments": "sbe41 aa4330 wlbb2fl qsp2150 ", "lat": "-3432.505", "t_mission": 343, "gc_pitch_errors": 0}]