[{"sim_pitch": 0, "lon": 32.39194, "project": "GINA2018", "gc_vbd_retries": 0, "t_mission": 74, "sm_cc": 270, "glider": 573, "gc_vbd_errors": 0, "platform_id": "SG573", "gc_roll_retries": 0, "start_time": 1537253008, "altim_ping_depth": 1000, "start_time_human": "18-09-2018 06:43:28", "t_abort": 94, "file_name": "sg573_22_data.json", "gc_roll_errors": 0, "lat": -28.797692078878804, "dive_number": 72, "mission_number": 22, "d_tgt": 175, "c_pitch": 2490, "d_abort": 1050, "c_roll_climb": 1987, "c_roll_dive": 2130, "t_dive": 59, "max_buoy": 150, "c_vbd": 2812, "instruments": "magnetometer wlbb2fl aa4831 sbe41 qsp2150 ", "gc_pitch_retries": 0, "gc_pitch_errors": 0}]