[{"gc_roll_retries": 0, "t_mission": 345, "instruments": "magnetometer wlbb2fl aa4831 sbe41 ", "max_buoy": 280, "t_dive": 335, "start_time_human": "23-04-2019 01:56:02", "gc_pitch_retries": 0, "gc_vbd_retries": 0, "c_vbd": 2812, "wp_lat": "0", "file_name": "sg573_30_data.json", "lat": "-3347.490", "d_tgt": 1000, "altim_ping_depth": 80, "c_roll_climb": 1964, "gc_pitch_errors": 0, "lon": "2714.295", "sim_pitch": 0, "c_pitch": 2490, "start_time": 1555984562, "gpsTime": "010170000000", "gc_roll_errors": 0, "sm_cc": 542, "d_abort": 1050, "platform_id": "SG573", "c_roll_dive": 2013, "dive_number": 353, "project": "GINA2019_1", "gc_vbd_errors": 0, "glider": 573, "t_abort": 360, "mission_number": 30}]