[{"c_roll_dive": 1987, "project": "GINA2019_1", "start_time_human": "04-04-2019 21:53:23", "lat": "-2909.937", "dive_number": 103, "mission_number": 30, "sm_cc": 542, "max_buoy": 150, "instruments": "magnetometer wlbb2fl aa4831 sbe41 ", "lon": "3211.229", "gc_vbd_errors": 0, "t_dive": 333, "t_mission": 343, "wp_lat": "0", "gc_roll_errors": 0, "d_abort": 1050, "gc_vbd_retries": 0, "sim_pitch": 0, "c_pitch": 2490, "t_abort": 358, "glider": 573, "gc_pitch_retries": 0, "gc_roll_retries": 0, "platform_id": "SG573", "start_time": 1554414803, "altim_ping_depth": 80, "file_name": "sg573_30_data.json", "gc_pitch_errors": 0, "c_roll_climb": 1987, "d_tgt": 1000, "c_vbd": 2812, "gpsTime": "010170000000"}]