[{"lat": "-2909.079", "c_roll_dive": 1987, "dive_number": 4, "gc_roll_errors": 0, "sim_pitch": 0, "glider": 573, "gc_roll_retries": 0, "d_abort": 1050, "project": "GINA2018_leg2", "file_name": "sg573_23_data.json", "gc_vbd_retries": 0, "sm_cc": 532, "c_vbd": 2812, "c_pitch": 2490, "t_abort": 360, "platform_id": "SG573", "start_time": 1538729544, "mission_number": 23, "c_roll_climb": 1987, "start_time_human": "05-10-2018 08:52:24", "wp_lon": "3117.47", "max_buoy": 150, "lon": "3209.051", "instruments": "magnetometer wlbb2fl aa4831 sbe41 qsp2150 ", "gpsTime": "010170000000", "gc_pitch_retries": 0, "gc_pitch_errors": 0, "wp_lat": "-2953.98", "t_dive": 333, "t_mission": 343, "altim_ping_depth": 100, "gc_vbd_errors": 0, "d_tgt": 500}]