[{"file_name": "sg573_30_data.json", "d_tgt": 500, "glider": 573, "gc_vbd_retries": 0, "gc_pitch_retries": 0, "gc_vbd_errors": 0, "platform_id": "SG573", "max_buoy": 150, "sm_cc": 542, "gc_pitch_errors": 0, "start_time": 1554084391, "gpsTime": "010170000000", "t_dive": 167, "t_abort": 197, "sim_pitch": 0, "gc_roll_retries": 0, "gc_roll_errors": 0, "mission_number": 30, "lon": "3215.710", "wp_lat": "0", "c_roll_climb": 1987, "project": "GINA2019_1", "start_time_human": "01-04-2019 02:06:31", "t_mission": 182, "c_pitch": 2490, "c_vbd": 2812, "instruments": "magnetometer wlbb2fl aa4831 sbe41 qsp2150 ", "d_abort": 1050, "altim_ping_depth": 100, "dive_number": 36, "lat": "-2854.609", "c_roll_dive": 1987}]