[{"glider": 574, "project": "GINA2019_1", "c_pitch": 2759, "c_roll_climb": 1800, "d_abort": 1020, "c_roll_dive": 1812, "lon": "3112.785", "sim_pitch": 0, "file_name": "sg574_3_data.json", "gc_roll_retries": 0, "lat": "-2958.988", "gc_pitch_retries": 0, "start_time_human": "31-03-2019 15:27:12", "gc_vbd_errors": 0, "dive_number": 213, "t_abort": 197, "mission_number": 3, "d_tgt": 500, "wp_lat": "0", "c_vbd": 2701, "sm_cc": 515, "platform_id": "SG574", "t_mission": 182, "gpsTime": "010170000000", "t_dive": 167, "max_buoy": 95, "instruments": "sbe41 aa4330 wlbb2fl qsp2150 ", "gc_vbd_retries": 0, "altim_ping_depth": 50, "gc_pitch_errors": 0, "start_time": 1554046032, "gc_roll_errors": 0}]