[{"gc_roll_retries": 0, "lat": "-2855.285", "project": "GINA2019_1", "sm_cc": 542, "t_dive": 33, "instruments": "magnetometer wlbb2fl aa4831 sbe41 qsp2150 ", "lon": "3212.837", "c_pitch": 2490, "dive_number": 51, "d_tgt": 100, "c_roll_dive": 1987, "max_buoy": 150, "file_name": "sg573_30_data.json", "gc_pitch_errors": 0, "mission_number": 30, "sim_pitch": 0, "start_time_human": "01-04-2019 23:20:30", "t_mission": 43, "gc_roll_errors": 0, "gc_pitch_retries": 0, "start_time": 1554160830, "c_vbd": 2812, "gc_vbd_retries": 0, "gpsTime": "010170000000", "wp_lat": "0", "t_abort": 60, "d_abort": 1050, "c_roll_climb": 1987, "gc_vbd_errors": 0, "platform_id": "SG573", "altim_ping_depth": 50, "glider": 573}]