[{"t_dive": 33, "start_time": 1554178325, "gc_pitch_retries": 0, "c_roll_climb": 1987, "altim_ping_depth": 50, "glider": 573, "lat": "-2852.641", "lon": "3215.628", "c_vbd": 2812, "file_name": "sg573_30_data.json", "gc_pitch_errors": 0, "dive_number": 60, "gc_roll_retries": 0, "gc_vbd_errors": 0, "gc_vbd_retries": 0, "d_abort": 1050, "start_time_human": "02-04-2019 04:12:05", "instruments": "magnetometer wlbb2fl aa4831 sbe41 qsp2150 ", "wp_lat": "0", "max_buoy": 150, "t_mission": 43, "mission_number": 30, "t_abort": 60, "d_tgt": 100, "platform_id": "SG573", "sm_cc": 542, "gpsTime": "010170000000", "c_pitch": 2490, "project": "GINA2019_1", "sim_pitch": 0, "c_roll_dive": 1987, "gc_roll_errors": 0}]